README
setup.py
seed_phrases_for_stellar/__init__.py
seed_phrases_for_stellar/electrum_mnemonic.py
seed_phrases_for_stellar/key_derivation.py
seed_phrases_for_stellar/old_electrum_mnemonic.py
seed_phrases_for_stellar/seed_phrase_to_stellar_keys.py
seed_phrases_for_stellar/version.py
seed_phrases_for_stellar.egg-info/PKG-INFO
seed_phrases_for_stellar.egg-info/SOURCES.txt
seed_phrases_for_stellar.egg-info/dependency_links.txt
seed_phrases_for_stellar.egg-info/entry_points.txt
seed_phrases_for_stellar.egg-info/requires.txt
seed_phrases_for_stellar.egg-info/top_level.txt