Metadata-Version: 1.1
Name: seed-phrases-for-stellar
Version: 0.2
Summary: Utility for generating Stellar accounts from BIP39/Electrum seed phrases
Home-page: https://github.com/reverbel/seed-phrases-for-stellar
Author: Francisco Reverbel
Author-email: reverbel@gmail.com
License: http://opensource.org/licenses/MIT
Keywords: Stellar deterministic keypair generation BIP39 Electrum mnemonic seed phrase
Platform: UNKNOWN
Classifier: Development Status :: 3 - Alpha
Classifier: Topic :: Utilities
Classifier: Topic :: Internet
Classifier: Topic :: Security :: Cryptography
Classifier: License :: OSI Approved :: MIT License
Classifier: Operating System :: POSIX :: Linux
Classifier: Operating System :: MacOS :: MacOS X
Classifier: Operating System :: Microsoft :: Windows
Classifier: Programming Language :: Python :: 3
Classifier: Programming Language :: Python :: 3.4
Classifier: Programming Language :: Python :: 3.5
Classifier: Programming Language :: Python :: 3.6
Classifier: Programming Language :: Python :: 3.7
